MANIFEST.in
readme.md
setup.py
bin/note
key_note/__init__.py
key_note/command.py
key_note/database.py
key_note.egg-info/PKG-INFO
key_note.egg-info/SOURCES.txt
key_note.egg-info/dependency_links.txt
key_note.egg-info/top_level.txt