Metadata-Version: 1.1
Name: key-note
Version: 0.1
Summary: notes linked with keywords
Home-page: https://github.com/dvector89/key_note
Author: dvector89
Author-email: shiliangliang.cas@gmail.com
License: MIT
Platform: UNKNOWN
Classifier: License :: OSI Approved :: MIT License
Classifier: Programming Language :: Python
